{
  "alerts": [
    {
      "ticker": "AMD",
      "type": "CALL",
      "strike": 192.5,
      "currentPrice": 184.0399932861328,
      "expiration": "2025-09-05",
      "daysToExpiration": 22,
      "volume": 2428.0,
      "openInterest": 480,
      "lastPrice": 5.6,
      "impliedVolatility": 0.48071808349609374,
      "timestamp": "2025-08-13T12:50:13.596253",
      "delta": 0.38202937270831694,
      "gamma": 0.01755816017109159,
      "theta": -0.19579486633584003,
      "vega": 0.1723152442325583,
      "score": 98,
      "sweep": true,
      "commentary": "\ud83c\udfaf HIGH CONFIDENCE | MASSIVE volume surge - potential big move | Balanced IV environment | Moderate time decay risk"
    },
    {
      "ticker": "AMD",
      "type": "PUT",
      "strike": 187.5,
      "currentPrice": 184.0399932861328,
      "expiration": "2025-09-05",
      "daysToExpiration": 22,
      "volume": 63.0,
      "openInterest": 15,
      "lastPrice": 9.9,
      "impliedVolatility": 0.4200497448730469,
      "timestamp": "2025-08-13T12:50:13.604213",
      "delta": -0.5415264467983856,
      "gamma": 0.020905997443427915,
      "theta": -0.15850735151520073,
      "vega": 0.17927752670351693,
      "score": 98,
      "sweep": true,
      "commentary": "\ud83c\udfaf HIGH CONFIDENCE | MASSIVE volume surge - potential big move | Balanced IV environment | Moderate time decay risk | Good price sensitivity"
    },
    {
      "ticker": "DKS",
      "type": "PUT",
      "strike": 225.0,
      "currentPrice": 224.125,
      "expiration": "2025-08-29",
      "daysToExpiration": 15,
      "volume": 8.0,
      "openInterest": 2,
      "lastPrice": 9.5,
      "impliedVolatility": 0.48413601806640627,
      "timestamp": "2025-08-13T12:50:10.254847",
      "delta": -0.4891833274094881,
      "gamma": 0.018129820337928138,
      "theta": -0.27862787499616964,
      "vega": 0.18119236514493584,
      "score": 93,
      "sweep": true,
      "commentary": "\ud83c\udfaf HIGH CONFIDENCE | MASSIVE volume surge - potential big move | Balanced IV environment | Short-term play - watch theta | Good price sensitivity"
    },
    {
      "ticker": "AMD",
      "type": "CALL",
      "strike": 187.5,
      "currentPrice": 184.0399932861328,
      "expiration": "2025-08-29",
      "daysToExpiration": 15,
      "volume": 2216.0,
      "openInterest": 541,
      "lastPrice": 6.2,
      "impliedVolatility": 0.5028125891113282,
      "timestamp": "2025-08-13T12:50:13.383548",
      "delta": 0.45435035797489753,
      "gamma": 0.021126951095874823,
      "theta": -0.2568310737911533,
      "vega": 0.14786513423087602,
      "score": 93,
      "sweep": true,
      "commentary": "\ud83c\udfaf HIGH CONFIDENCE | MASSIVE volume surge - potential big move | Balanced IV environment | Short-term play - watch theta | Good price sensitivity"
    },
    {
      "ticker": "AMD",
      "type": "CALL",
      "strike": 190.0,
      "currentPrice": 184.0399932861328,
      "expiration": "2025-08-29",
      "daysToExpiration": 15,
      "volume": 7668.0,
      "openInterest": 2469,
      "lastPrice": 5.4,
      "impliedVolatility": 0.5009815527343751,
      "timestamp": "2025-08-13T12:50:13.383608",
      "delta": 0.4028849220597275,
      "gamma": 0.020708475640561743,
      "theta": -0.24917225549824676,
      "vega": 0.1444084737742987,
      "score": 93,
      "sweep": true,
      "commentary": "\ud83c\udfaf HIGH CONFIDENCE | MASSIVE volume surge - potential big move | Balanced IV environment | Short-term play - watch theta | Good price sensitivity"
    },
    {
      "ticker": "AMD",
      "type": "PUT",
      "strike": 182.5,
      "currentPrice": 184.0399932861328,
      "expiration": "2025-08-29",
      "daysToExpiration": 15,
      "volume": 2309.0,
      "openInterest": 143,
      "lastPrice": 6.2,
      "impliedVolatility": 0.44165597412109375,
      "timestamp": "2025-08-13T12:50:13.387783",
      "delta": -0.43720013823711656,
      "gamma": 0.023910505817596874,
      "theta": -0.2064020133246944,
      "vega": 0.14699267217642248,
      "score": 93,
      "sweep": true,
      "commentary": "\ud83c\udfaf HIGH CONFIDENCE | MASSIVE volume surge - potential big move | Balanced IV environment | Short-term play - watch theta | Good price sensitivity"
    },
    {
      "ticker": "AMD",
      "type": "PUT",
      "strike": 185.0,
      "currentPrice": 184.0399932861328,
      "expiration": "2025-08-29",
      "daysToExpiration": 15,
      "volume": 2331.0,
      "openInterest": 114,
      "lastPrice": 7.4,
      "impliedVolatility": 0.4398249377441406,
      "timestamp": "2025-08-13T12:50:13.387860",
      "delta": -0.49770097490409226,
      "gamma": 0.024311491215383736,
      "theta": -0.2067750423724161,
      "vega": 0.14883814900070197,
      "score": 93,
      "sweep": true,
      "commentary": "\ud83c\udfaf HIGH CONFIDENCE | MASSIVE volume surge - potential big move | Balanced IV environment | Short-term play - watch theta | Good price sensitivity"
    },
    {
      "ticker": "AMD",
      "type": "PUT",
      "strike": 187.5,
      "currentPrice": 184.0399932861328,
      "expiration": "2025-08-29",
      "daysToExpiration": 15,
      "volume": 284.0,
      "openInterest": 60,
      "lastPrice": 8.9,
      "impliedVolatility": 0.43543045043945316,
      "timestamp": "2025-08-13T12:50:13.387930",
      "delta": -0.5584894004040912,
      "gamma": 0.024292855138749885,
      "theta": -0.20081781891994224,
      "vega": 0.1472380880432889,
      "score": 93,
      "sweep": true,
      "commentary": "\ud83c\udfaf HIGH CONFIDENCE | MASSIVE volume surge - potential big move | Balanced IV environment | Short-term play - watch theta | Good price sensitivity"
    },
    {
      "ticker": "AMD",
      "type": "PUT",
      "strike": 195.0,
      "currentPrice": 184.0399932861328,
      "expiration": "2025-09-05",
      "daysToExpiration": 22,
      "volume": 29.0,
      "openInterest": 4,
      "lastPrice": 16.8,
      "impliedVolatility": 0.41235939208984373,
      "timestamp": "2025-08-13T12:50:13.604556",
      "delta": -0.6898918891104583,
      "gamma": 0.018937975912655773,
      "theta": -0.1330467508700675,
      "vega": 0.1594276646322866,
      "score": 93,
      "sweep": true,
      "commentary": "\ud83c\udfaf HIGH CONFIDENCE | MASSIVE volume surge - potential big move | Balanced IV environment | Moderate time decay risk | High delta sensitivity"
    },
    {
      "ticker": "TSLA",
      "type": "PUT",
      "strike": 320.0,
      "currentPrice": 340.114990234375,
      "expiration": "2025-09-05",
      "daysToExpiration": 22,
      "volume": 2841.0,
      "openInterest": 864,
      "lastPrice": 6.43,
      "impliedVolatility": 0.42407802490234375,
      "timestamp": "2025-08-13T12:50:08.226166",
      "delta": -0.2539444627152494,
      "gamma": 0.00904842969578127,
      "theta": -0.24717678869406723,
      "vega": 0.26754716177258187,
      "score": 88,
      "sweep": true,
      "commentary": "\ud83c\udfaf HIGH CONFIDENCE | MASSIVE volume surge - potential big move | Balanced IV environment | Moderate time decay risk"
    },
    {
      "ticker": "AMD",
      "type": "CALL",
      "strike": 185.0,
      "currentPrice": 184.0399932861328,
      "expiration": "2025-09-05",
      "daysToExpiration": 22,
      "volume": 2430.0,
      "openInterest": 1109,
      "lastPrice": 8.57,
      "impliedVolatility": 0.4821829125976563,
      "timestamp": "2025-08-13T12:50:13.595859",
      "delta": 0.5146850608843417,
      "gamma": 0.01829897529503037,
      "theta": -0.20741854926332431,
      "vega": 0.1801328086515632,
      "score": 88,
      "sweep": false,
      "commentary": "\ud83c\udfaf HIGH CONFIDENCE | Strong volume activity above normal | Balanced IV environment | Moderate time decay risk | Good price sensitivity"
    },
    {
      "ticker": "PLTR",
      "type": "PUT",
      "strike": 202.5,
      "currentPrice": 185.7050018310547,
      "expiration": "2025-08-29",
      "daysToExpiration": 15,
      "volume": 31,
      "openInterest": 9,
      "lastPrice": 19.45,
      "impliedVolatility": 0.47400428344726564,
      "timestamp": "2025-08-13T12:50:09.373266",
      "delta": -0.798101217027811,
      "gamma": 0.01577814497086717,
      "theta": -0.14813126597328027,
      "vega": 0.10599461594141811,
      "score": 83,
      "sweep": true,
      "commentary": "\ud83c\udfaf HIGH CONFIDENCE | MASSIVE volume surge - potential big move | Balanced IV environment | Short-term play - watch theta | High delta sensitivity"
    },
    {
      "ticker": "PLTR",
      "type": "PUT",
      "strike": 197.5,
      "currentPrice": 185.7050018310547,
      "expiration": "2025-09-05",
      "daysToExpiration": 22,
      "volume": 3.0,
      "openInterest": 1,
      "lastPrice": 15.89,
      "impliedVolatility": 0.44434149414062496,
      "timestamp": "2025-08-13T12:50:09.627948",
      "delta": -0.6867022389618462,
      "gamma": 0.017494626125671087,
      "theta": -0.14661179677968758,
      "vega": 0.16158407473553305,
      "score": 83,
      "sweep": false,
      "commentary": "\ud83c\udfaf HIGH CONFIDENCE | Strong volume activity above normal | Balanced IV environment | Moderate time decay risk | High delta sensitivity"
    },
    {
      "ticker": "RBLX",
      "type": "PUT",
      "strike": 117.0,
      "currentPrice": 126.01000213623047,
      "expiration": "2025-08-29",
      "daysToExpiration": 15,
      "volume": 458.0,
      "openInterest": 127,
      "lastPrice": 1.9,
      "impliedVolatility": 0.4939015454101563,
      "timestamp": "2025-08-13T12:50:10.922136",
      "delta": -0.20942749234246372,
      "gamma": 0.022806265456924102,
      "theta": -0.11776390816692371,
      "vega": 0.07350264924405493,
      "score": 83,
      "sweep": true,
      "commentary": "\ud83c\udfaf HIGH CONFIDENCE | MASSIVE volume surge - potential big move | Balanced IV environment | Short-term play - watch theta"
    },
    {
      "ticker": "RBLX",
      "type": "CALL",
      "strike": 110.0,
      "currentPrice": 126.01000213623047,
      "expiration": "2025-09-05",
      "daysToExpiration": 22,
      "volume": 19.0,
      "openInterest": 5,
      "lastPrice": 20.43,
      "impliedVolatility": 0.5256395092773438,
      "timestamp": "2025-08-13T12:50:11.053241",
      "delta": 0.8722858534007387,
      "gamma": 0.012849935793798374,
      "theta": -0.08796961160812566,
      "vega": 0.06464408804056976,
      "score": 83,
      "sweep": true,
      "commentary": "\ud83c\udfaf HIGH CONFIDENCE | MASSIVE volume surge - potential big move | Balanced IV environment | Moderate time decay risk | High delta sensitivity"
    },
    {
      "ticker": "AMD",
      "type": "CALL",
      "strike": 182.5,
      "currentPrice": 184.0399932861328,
      "expiration": "2025-08-29",
      "daysToExpiration": 15,
      "volume": 1842.0,
      "openInterest": 772,
      "lastPrice": 8.67,
      "impliedVolatility": 0.5042774182128906,
      "timestamp": "2025-08-13T12:50:13.383415",
      "delta": 0.5597552732628517,
      "gamma": 0.020966241267693305,
      "theta": -0.258360553150912,
      "vega": 0.14716783869507144,
      "score": 83,
      "sweep": false,
      "commentary": "\ud83c\udfaf HIGH CONFIDENCE | Strong volume activity above normal | Balanced IV environment | Short-term play - watch theta | Good price sensitivity"
    },
    {
      "ticker": "AMD",
      "type": "CALL",
      "strike": 185.0,
      "currentPrice": 184.0399932861328,
      "expiration": "2025-08-29",
      "daysToExpiration": 15,
      "volume": 5909.0,
      "openInterest": 2473,
      "lastPrice": 7.5,
      "impliedVolatility": 0.5035450036621094,
      "timestamp": "2025-08-13T12:50:13.383481",
      "delta": 0.5068350201205372,
      "gamma": 0.021232279480118844,
      "theta": -0.25978549100245685,
      "vega": 0.14881877501846583,
      "score": 83,
      "sweep": false,
      "commentary": "\ud83c\udfaf HIGH CONFIDENCE | Strong volume activity above normal | Balanced IV environment | Short-term play - watch theta | Good price sensitivity"
    },
    {
      "ticker": "AMD",
      "type": "PUT",
      "strike": 180.0,
      "currentPrice": 184.0399932861328,
      "expiration": "2025-08-29",
      "daysToExpiration": 15,
      "volume": 2990.0,
      "openInterest": 1117,
      "lastPrice": 5.1,
      "impliedVolatility": 0.44714908325195313,
      "timestamp": "2025-08-13T12:50:13.387706",
      "delta": -0.37850768839201043,
      "gamma": 0.022796009604737773,
      "theta": -0.20285261183939138,
      "vega": 0.14188418440826447,
      "score": 83,
      "sweep": false,
      "commentary": "\ud83c\udfaf HIGH CONFIDENCE | Strong volume activity above normal | Balanced IV environment | Short-term play - watch theta"
    },
    {
      "ticker": "AMD",
      "type": "PUT",
      "strike": 190.0,
      "currentPrice": 184.0399932861328,
      "expiration": "2025-08-29",
      "daysToExpiration": 15,
      "volume": 395.0,
      "openInterest": 153,
      "lastPrice": 10.35,
      "impliedVolatility": 0.43506424316406256,
      "timestamp": "2025-08-13T12:50:13.388000",
      "delta": -0.6169639685048394,
      "gamma": 0.023513875983835836,
      "theta": -0.19218816032648042,
      "vega": 0.14239686454233172,
      "score": 83,
      "sweep": false,
      "commentary": "\ud83c\udfaf HIGH CONFIDENCE | Strong volume activity above normal | Balanced IV environment | Short-term play - watch theta | High delta sensitivity"
    },
    {
      "ticker": "AMD",
      "type": "PUT",
      "strike": 197.5,
      "currentPrice": 184.0399932861328,
      "expiration": "2025-08-29",
      "daysToExpiration": 15,
      "volume": 26.0,
      "openInterest": 3,
      "lastPrice": 16.25,
      "impliedVolatility": 0.42200285034179685,
      "timestamp": "2025-08-13T12:50:13.388225",
      "delta": -0.7769569425697682,
      "gamma": 0.01895450773997118,
      "theta": -0.13826813319861378,
      "vega": 0.11133986911836263,
      "score": 83,
      "sweep": true,
      "commentary": "\ud83c\udfaf HIGH CONFIDENCE | MASSIVE volume surge - potential big move | Balanced IV environment | Short-term play - watch theta | High delta sensitivity"
    },
    {
      "ticker": "AMD",
      "type": "PUT",
      "strike": 205.0,
      "currentPrice": 184.0399932861328,
      "expiration": "2025-09-05",
      "daysToExpiration": 22,
      "volume": 45.0,
      "openInterest": 9,
      "lastPrice": 22.85,
      "impliedVolatility": 0.4112607702636719,
      "timestamp": "2025-08-13T12:50:13.604931",
      "delta": -0.8395107681474623,
      "gamma": 0.01312004506732952,
      "theta": -0.0824740719726285,
      "vega": 0.11015566720008352,
      "score": 83,
      "sweep": true,
      "commentary": "\ud83c\udfaf HIGH CONFIDENCE | MASSIVE volume surge - potential big move | Balanced IV environment | Moderate time decay risk | High delta sensitivity"
    },
    {
      "ticker": "AMD",
      "type": "PUT",
      "strike": 225.0,
      "currentPrice": 184.0399932861328,
      "expiration": "2025-09-05",
      "daysToExpiration": 22,
      "volume": 6.0,
      "openInterest": 1,
      "lastPrice": 41.3,
      "impliedVolatility": 0.397466962890625,
      "timestamp": "2025-08-13T12:50:13.605271",
      "delta": -0.9763896990255366,
      "gamma": 0.0031017894526658694,
      "theta": 0.0028352530360862033,
      "vega": 0.0251690941337423,
      "score": 83,
      "sweep": true,
      "commentary": "\ud83c\udfaf HIGH CONFIDENCE | MASSIVE volume surge - potential big move | Balanced IV environment | Moderate time decay risk | High delta sensitivity"
    },
    {
      "ticker": "TSLA",
      "type": "PUT",
      "strike": 375.0,
      "currentPrice": 340.114990234375,
      "expiration": "2025-08-29",
      "daysToExpiration": 15,
      "volume": 111.0,
      "openInterest": 18,
      "lastPrice": 36.25,
      "impliedVolatility": 0.4271297521972657,
      "timestamp": "2025-08-13T12:50:08.022381",
      "delta": -0.8563930382367185,
      "gamma": 0.0076891200665246875,
      "theta": -0.1842560199421933,
      "vega": 0.1561300172800059,
      "score": 78,
      "sweep": true,
      "commentary": "\u2705 GOOD SETUP | MASSIVE volume surge - potential big move | Balanced IV environment | Short-term play - watch theta | High delta sensitivity"
    },
    {
      "ticker": "TSLA",
      "type": "PUT",
      "strike": 430.0,
      "currentPrice": 340.114990234375,
      "expiration": "2025-08-29",
      "daysToExpiration": 15,
      "volume": 202.0,
      "openInterest": 27,
      "lastPrice": 95.65,
      "impliedVolatility": 0.62305064453125,
      "timestamp": "2025-08-13T12:50:08.023936",
      "delta": -0.9624356511623913,
      "gamma": 0.0019059058448668408,
      "theta": -0.06881181572085507,
      "vega": 0.0564514020944062,
      "score": 78,
      "sweep": true,
      "commentary": "\u2705 GOOD SETUP | MASSIVE volume surge - potential big move | Elevated IV suggests catalyst | Short-term play - watch theta | High delta sensitivity"
    },
    {
      "ticker": "TSLA",
      "type": "PUT",
      "strike": 440.0,
      "currentPrice": 340.114990234375,
      "expiration": "2025-08-29",
      "daysToExpiration": 15,
      "volume": 9.0,
      "openInterest": 1,
      "lastPrice": 98.2,
      "impliedVolatility": 0.6113320117187502,
      "timestamp": "2025-08-13T12:50:08.024143",
      "delta": -0.9773412285618761,
      "gamma": 0.0012765743039656508,
      "theta": -0.0254570648137414,
      "vega": 0.03709993746340741,
      "score": 78,
      "sweep": true,
      "commentary": "\u2705 GOOD SETUP | MASSIVE volume surge - potential big move | Elevated IV suggests catalyst | Short-term play - watch theta | High delta sensitivity"
    },
    {
      "ticker": "TSLA",
      "type": "CALL",
      "strike": 345.0,
      "currentPrice": 340.114990234375,
      "expiration": "2025-09-05",
      "daysToExpiration": 22,
      "volume": 1769.0,
      "openInterest": 1210,
      "lastPrice": 13.85,
      "impliedVolatility": 0.4621635815429688,
      "timestamp": "2025-08-13T12:50:08.202839",
      "delta": 0.4814803914556425,
      "gamma": 0.010326553024881478,
      "theta": -0.36696257064987275,
      "vega": 0.33276103221666675,
      "score": 78,
      "sweep": false,
      "commentary": "\u2705 GOOD SETUP | Balanced IV environment | Moderate time decay risk | Good price sensitivity"
    },
    {
      "ticker": "RBLX",
      "type": "CALL",
      "strike": 121.0,
      "currentPrice": 126.01000213623047,
      "expiration": "2025-09-05",
      "daysToExpiration": 22,
      "volume": 4.0,
      "openInterest": 2,
      "lastPrice": 7.65,
      "impliedVolatility": 0.5136767382812499,
      "timestamp": "2025-08-13T12:50:11.053695",
      "delta": 0.6572671881487052,
      "gamma": 0.02312756012885358,
      "theta": -0.14128442309645645,
      "vega": 0.11369976634898583,
      "score": 78,
      "sweep": false,
      "commentary": "\u2705 GOOD SETUP | Elevated volume interest | Balanced IV environment | Moderate time decay risk | High delta sensitivity"
    },
    {
      "ticker": "RBLX",
      "type": "CALL",
      "strike": 124.0,
      "currentPrice": 126.01000213623047,
      "expiration": "2025-09-05",
      "daysToExpiration": 22,
      "volume": 41.0,
      "openInterest": 23,
      "lastPrice": 6.3,
      "impliedVolatility": 0.47192910888671874,
      "timestamp": "2025-08-13T12:50:11.053905",
      "delta": 0.5865819790562269,
      "gamma": 0.026679118154079865,
      "theta": -0.13701344741791088,
      "vega": 0.12050028951583742,
      "score": 78,
      "sweep": false,
      "commentary": "\u2705 GOOD SETUP | Elevated volume interest | Balanced IV environment | Moderate time decay risk | Good price sensitivity"
    },
    {
      "ticker": "RBLX",
      "type": "CALL",
      "strike": 125.0,
      "currentPrice": 126.01000213623047,
      "expiration": "2025-09-05",
      "daysToExpiration": 22,
      "volume": 58.0,
      "openInterest": 31,
      "lastPrice": 6.21,
      "impliedVolatility": 0.46130909790039065,
      "timestamp": "2025-08-13T12:50:11.053966",
      "delta": 0.5597119482864479,
      "gamma": 0.02764055301677513,
      "theta": -0.135395300296731,
      "vega": 0.12203336923984479,
      "score": 78,
      "sweep": false,
      "commentary": "\u2705 GOOD SETUP | Elevated volume interest | Balanced IV environment | Moderate time decay risk | Good price sensitivity"
    },
    {
      "ticker": "RBLX",
      "type": "CALL",
      "strike": 127.0,
      "currentPrice": 126.01000213623047,
      "expiration": "2025-09-05",
      "daysToExpiration": 22,
      "volume": 14.0,
      "openInterest": 7,
      "lastPrice": 4.5,
      "impliedVolatility": 0.48071808349609374,
      "timestamp": "2025-08-13T12:50:11.054086",
      "delta": 0.5057225183657021,
      "gamma": 0.02682285466971446,
      "theta": -0.1415727229434675,
      "vega": 0.12340572571627625,
      "score": 78,
      "sweep": false,
      "commentary": "\u2705 GOOD SETUP | Elevated volume interest | Balanced IV environment | Moderate time decay risk | Good price sensitivity"
    },
    {
      "ticker": "RBLX",
      "type": "PUT",
      "strike": 123.0,
      "currentPrice": 126.01000213623047,
      "expiration": "2025-09-05",
      "daysToExpiration": 22,
      "volume": 20.0,
      "openInterest": 11,
      "lastPrice": 4.55,
      "impliedVolatility": 0.4519097778320313,
      "timestamp": "2025-08-13T12:50:11.058082",
      "delta": -0.38345812235661425,
      "gamma": 0.02730926174126887,
      "theta": -0.11523656779842034,
      "vega": 0.11811404755384203,
      "score": 78,
      "sweep": false,
      "commentary": "\u2705 GOOD SETUP | Elevated volume interest | Balanced IV environment | Moderate time decay risk"
    },
    {
      "ticker": "AAPL",
      "type": "CALL",
      "strike": 165.0,
      "currentPrice": 232.47999572753906,
      "expiration": "2025-08-29",
      "daysToExpiration": 15,
      "volume": 8,
      "openInterest": 2,
      "lastPrice": 67.51,
      "impliedVolatility": 0.570316796875,
      "timestamp": "2025-08-13T12:50:11.749865",
      "delta": 0.9988107495857347,
      "gamma": 0.0001468429773030094,
      "theta": -0.022627744850337927,
      "vega": 0.0018601112376757582,
      "score": 78,
      "sweep": true,
      "commentary": "\u2705 GOOD SETUP | MASSIVE volume surge - potential big move | Balanced IV environment | Short-term play - watch theta | High delta sensitivity"
    },
    {
      "ticker": "AMD",
      "type": "CALL",
      "strike": 187.5,
      "currentPrice": 184.0399932861328,
      "expiration": "2025-09-05",
      "daysToExpiration": 22,
      "volume": 710.0,
      "openInterest": 441,
      "lastPrice": 7.36,
      "impliedVolatility": 0.4819387744140625,
      "timestamp": "2025-08-13T12:50:13.595988",
      "delta": 0.46944298963567044,
      "gamma": 0.018266890353647446,
      "theta": -0.20603551587337823,
      "vega": 0.179725923850503,
      "score": 78,
      "sweep": false,
      "commentary": "\u2705 GOOD SETUP | Elevated volume interest | Balanced IV environment | Moderate time decay risk | Good price sensitivity"
    },
    {
      "ticker": "AMD",
      "type": "PUT",
      "strike": 180.0,
      "currentPrice": 184.0399932861328,
      "expiration": "2025-09-05",
      "daysToExpiration": 22,
      "volume": 395.0,
      "openInterest": 381,
      "lastPrice": 6.0,
      "impliedVolatility": 0.428716650390625,
      "timestamp": "2025-08-13T12:50:13.603872",
      "delta": -0.3867575623244117,
      "gamma": 0.01975964054441142,
      "theta": -0.15959469702785165,
      "vega": 0.17294325339141275,
      "score": 78,
      "sweep": false,
      "commentary": "\u2705 GOOD SETUP | Balanced IV environment | Moderate time decay risk"
    },
    {
      "ticker": "AMD",
      "type": "PUT",
      "strike": 182.5,
      "currentPrice": 184.0399932861328,
      "expiration": "2025-09-05",
      "daysToExpiration": 22,
      "volume": 589.0,
      "openInterest": 558,
      "lastPrice": 7.13,
      "impliedVolatility": 0.42529871582031253,
      "timestamp": "2025-08-13T12:50:13.603987",
      "delta": -0.437564051656682,
      "gamma": 0.02050578077171132,
      "theta": -0.16197058982310147,
      "vega": 0.17804288183495548,
      "score": 78,
      "sweep": false,
      "commentary": "\u2705 GOOD SETUP | Balanced IV environment | Moderate time decay risk | Good price sensitivity"
    },
    {
      "ticker": "AMD",
      "type": "PUT",
      "strike": 190.0,
      "currentPrice": 184.0399932861328,
      "expiration": "2025-09-05",
      "daysToExpiration": 22,
      "volume": 84.0,
      "openInterest": 43,
      "lastPrice": 11.85,
      "impliedVolatility": 0.4211483666992188,
      "timestamp": "2025-08-13T12:50:13.604330",
      "delta": -0.5916695074523272,
      "gamma": 0.020409202822120862,
      "theta": -0.15406594077255414,
      "vega": 0.1754750586476399,
      "score": 78,
      "sweep": false,
      "commentary": "\u2705 GOOD SETUP | Elevated volume interest | Balanced IV environment | Moderate time decay risk | Good price sensitivity"
    },
    {
      "ticker": "TSLA",
      "type": "CALL",
      "strike": 350.0,
      "currentPrice": 340.114990234375,
      "expiration": "2025-08-29",
      "daysToExpiration": 15,
      "volume": 8366,
      "openInterest": 7427,
      "lastPrice": 9.35,
      "impliedVolatility": 0.46796186340332036,
      "timestamp": "2025-08-13T12:50:08.006644",
      "delta": 0.4066359474983151,
      "gamma": 0.012024282055193743,
      "theta": -0.4322839133344657,
      "vega": 0.2674973956920141,
      "score": 73,
      "sweep": false,
      "commentary": "\u2705 GOOD SETUP | Balanced IV environment | Short-term play - watch theta | Good price sensitivity"
    },
    {
      "ticker": "TSLA",
      "type": "PUT",
      "strike": 335.0,
      "currentPrice": 340.114990234375,
      "expiration": "2025-08-29",
      "daysToExpiration": 15,
      "volume": 1379.0,
      "openInterest": 1234,
      "lastPrice": 9.8,
      "impliedVolatility": 0.417425259399414,
      "timestamp": "2025-08-13T12:50:08.021160",
      "delta": -0.40440399612029054,
      "gamma": 0.013461489991965852,
      "theta": -0.3547014228873219,
      "vega": 0.26712946840745166,
      "score": 73,
      "sweep": false,
      "commentary": "\u2705 GOOD SETUP | Balanced IV environment | Short-term play - watch theta | Good price sensitivity"
    },
    {
      "ticker": "TSLA",
      "type": "PUT",
      "strike": 345.0,
      "currentPrice": 340.114990234375,
      "expiration": "2025-08-29",
      "daysToExpiration": 15,
      "volume": 1234.0,
      "openInterest": 1034,
      "lastPrice": 14.59,
      "impliedVolatility": 0.41687594848632803,
      "timestamp": "2025-08-13T12:50:08.021445",
      "delta": -0.5421621288679184,
      "gamma": 0.013802056626796469,
      "theta": -0.3570766493446743,
      "vega": 0.27352724156730346,
      "score": 73,
      "sweep": false,
      "commentary": "\u2705 GOOD SETUP | Balanced IV environment | Short-term play - watch theta | Good price sensitivity"
    },
    {
      "ticker": "PLTR",
      "type": "CALL",
      "strike": 190.0,
      "currentPrice": 185.7050018310547,
      "expiration": "2025-08-29",
      "daysToExpiration": 15,
      "volume": 2800,
      "openInterest": 2186,
      "lastPrice": 5.15,
      "impliedVolatility": 0.4422663195800781,
      "timestamp": "2025-08-13T12:50:09.358450",
      "delta": 0.4243527371073157,
      "gamma": 0.02352884911569027,
      "theta": -0.22599601798464988,
      "vega": 0.14747898814156954,
      "score": 73,
      "sweep": false,
      "commentary": "\u2705 GOOD SETUP | Balanced IV environment | Short-term play - watch theta | Good price sensitivity"
    },
    {
      "ticker": "PLTR",
      "type": "PUT",
      "strike": 180.0,
      "currentPrice": 185.7050018310547,
      "expiration": "2025-08-29",
      "daysToExpiration": 15,
      "volume": 2997,
      "openInterest": 2370,
      "lastPrice": 4.85,
      "impliedVolatility": 0.4669242761230469,
      "timestamp": "2025-08-13T12:50:09.371483",
      "delta": -0.3462845487829458,
      "gamma": 0.020989241222741737,
      "theta": -0.20821328449071025,
      "vega": 0.1388956965841175,
      "score": 73,
      "sweep": false,
      "commentary": "\u2705 GOOD SETUP | Balanced IV environment | Short-term play - watch theta"
    },
    {
      "ticker": "PLTR",
      "type": "PUT",
      "strike": 190.0,
      "currentPrice": 185.7050018310547,
      "expiration": "2025-08-29",
      "daysToExpiration": 15,
      "volume": 476,
      "openInterest": 356,
      "lastPrice": 10.2,
      "impliedVolatility": 0.45435115966796874,
      "timestamp": "2025-08-13T12:50:09.372262",
      "delta": -0.572710452445508,
      "gamma": 0.022935139716741892,
      "theta": -0.2102702270638464,
      "vega": 0.14768576202427916,
      "score": 73,
      "sweep": false,
      "commentary": "\u2705 GOOD SETUP | Balanced IV environment | Short-term play - watch theta | Good price sensitivity"
    },
    {
      "ticker": "RBLX",
      "type": "CALL",
      "strike": 121.0,
      "currentPrice": 126.01000213623047,
      "expiration": "2025-08-29",
      "daysToExpiration": 15,
      "volume": 27.0,
      "openInterest": 16,
      "lastPrice": 6.7,
      "impliedVolatility": 0.4858449853515625,
      "timestamp": "2025-08-13T12:50:10.910199",
      "delta": 0.6839779599782057,
      "gamma": 0.028662658864636488,
      "theta": -0.15625349759542684,
      "vega": 0.09087044018579532,
      "score": 73,
      "sweep": false,
      "commentary": "\u2705 GOOD SETUP | Elevated volume interest | Balanced IV environment | Short-term play - watch theta | High delta sensitivity"
    },
    {
      "ticker": "RBLX",
      "type": "CALL",
      "strike": 122.0,
      "currentPrice": 126.01000213623047,
      "expiration": "2025-08-29",
      "daysToExpiration": 15,
      "volume": 19.0,
      "openInterest": 12,
      "lastPrice": 6.37,
      "impliedVolatility": 0.477544287109375,
      "timestamp": "2025-08-13T12:50:10.910309",
      "delta": 0.6555908987765415,
      "gamma": 0.030183443864930156,
      "theta": -0.15847858382727698,
      "vega": 0.09405694675442278,
      "score": 73,
      "sweep": false,
      "commentary": "\u2705 GOOD SETUP | Elevated volume interest | Balanced IV environment | Short-term play - watch theta | High delta sensitivity"
    },
    {
      "ticker": "RBLX",
      "type": "CALL",
      "strike": 123.0,
      "currentPrice": 126.01000213623047,
      "expiration": "2025-08-29",
      "daysToExpiration": 15,
      "volume": 21.0,
      "openInterest": 14,
      "lastPrice": 5.95,
      "impliedVolatility": 0.4859670544433594,
      "timestamp": "2025-08-13T12:50:10.910420",
      "delta": 0.622612106331513,
      "gamma": 0.030606510023945904,
      "theta": -0.16555777726882484,
      "vega": 0.09705749344278157,
      "score": 73,
      "sweep": false,
      "commentary": "\u2705 GOOD SETUP | Balanced IV environment | Short-term play - watch theta | High delta sensitivity"
    },
    {
      "ticker": "RBLX",
      "type": "CALL",
      "strike": 124.0,
      "currentPrice": 126.01000213623047,
      "expiration": "2025-08-29",
      "daysToExpiration": 15,
      "volume": 62.0,
      "openInterest": 42,
      "lastPrice": 4.95,
      "impliedVolatility": 0.47241738525390625,
      "timestamp": "2025-08-13T12:50:10.910529",
      "delta": 0.5924964258934886,
      "gamma": 0.03216568211431441,
      "theta": -0.16412247481376677,
      "vega": 0.09915784270224118,
      "score": 73,
      "sweep": false,
      "commentary": "\u2705 GOOD SETUP | Balanced IV environment | Short-term play - watch theta | Good price sensitivity"
    },
    {
      "ticker": "RBLX",
      "type": "CALL",
      "strike": 125.0,
      "currentPrice": 126.01000213623047,
      "expiration": "2025-08-29",
      "daysToExpiration": 15,
      "volume": 85.0,
      "openInterest": 45,
      "lastPrice": 5.0,
      "impliedVolatility": 0.47022014160156256,
      "timestamp": "2025-08-13T12:50:10.910641",
      "delta": 0.5597581713246254,
      "gamma": 0.03283942784877994,
      "theta": -0.165499635806694,
      "vega": 0.10076396359450275,
      "score": 73,
      "sweep": false,
      "commentary": "\u2705 GOOD SETUP | Elevated volume interest | Balanced IV environment | Short-term play - watch theta | Good price sensitivity"
    },
    {
      "ticker": "RBLX",
      "type": "PUT",
      "strike": 135.0,
      "currentPrice": 126.01000213623047,
      "expiration": "2025-09-05",
      "daysToExpiration": 22,
      "volume": 10.0,
      "openInterest": 9,
      "lastPrice": 7.25,
      "impliedVolatility": 0.4735160070800781,
      "timestamp": "2025-08-13T12:50:11.058872",
      "delta": -0.6959180883060313,
      "gamma": 0.023879581330490108,
      "theta": -0.10496531963956511,
      "vega": 0.10821842955875768,
      "score": 73,
      "sweep": false,
      "commentary": "\u2705 GOOD SETUP | Balanced IV environment | Moderate time decay risk | High delta sensitivity"
    },
    {
      "ticker": "RBLX",
      "type": "PUT",
      "strike": 140.0,
      "currentPrice": 126.01000213623047,
      "expiration": "2025-09-05",
      "daysToExpiration": 22,
      "volume": 5.0,
      "openInterest": 2,
      "lastPrice": 13.25,
      "impliedVolatility": 0.5039112109375,
      "timestamp": "2025-08-13T12:50:11.059261",
      "delta": -0.7789047119314778,
      "gamma": 0.019047626089408073,
      "theta": -0.0920090925317531,
      "vega": 0.09186175366385207,
      "score": 73,
      "sweep": false,
      "commentary": "\u2705 GOOD SETUP | Strong volume activity above normal | Balanced IV environment | Moderate time decay risk | High delta sensitivity"
    },
    {
      "ticker": "AAPL",
      "type": "CALL",
      "strike": 295.0,
      "currentPrice": 232.47999572753906,
      "expiration": "2025-09-05",
      "daysToExpiration": 22,
      "volume": 42.0,
      "openInterest": 4,
      "lastPrice": 0.02,
      "impliedVolatility": 0.35156898437499995,
      "timestamp": "2025-08-13T12:50:11.954074",
      "delta": 0.0036087032575330283,
      "gamma": 0.0005383557291130156,
      "theta": -0.005021395733441034,
      "vega": 0.006165678676815003,
      "score": 73,
      "sweep": true,
      "commentary": "\u2705 GOOD SETUP | MASSIVE volume surge - potential big move | Balanced IV environment | Moderate time decay risk"
    }
  ],
  "last_updated": "2025-08-13T12:50:14.464058",
  "total": 918
}